djpress_publish_mastodon/__init__.py
djpress_publish_mastodon/plugin.py
djpress_publish_mastodon-1.3.0.dist-info/METADATA
djpress_publish_mastodon-1.3.0.dist-info/WHEEL
djpress_publish_mastodon-1.3.0.dist-info/entry_points.txt
djpress_publish_mastodon-1.3.0.dist-info/licenses/LICENSE
djpress_publish_mastodon-1.3.0.dist-info/RECORD
