Metadata-Version: 2.4
Name: djpress-publish-mastodon
Version: 1.3.0
Summary: A plugin for DJ Press that publishes new posts to Mastodon.
Author-email: Stuart Maxwell <stuart@amanzi.nz>
License-File: LICENSE
Requires-Python: >=3.10
Requires-Dist: djpress>=0.20
Requires-Dist: mastodon-py>=1.8.1
